flit_scm/__init__.py
flit_scm/_version.py
flit_scm-1.7.0.dist-info/LICENSE
flit_scm-1.7.0.dist-info/WHEEL
flit_scm-1.7.0.dist-info/METADATA
flit_scm-1.7.0.dist-info/RECORD
