Metadata-Version: 2.1
Name: flit_scm
Version: 1.7.0
Summary: A PEP 518 build backend that uses setuptools_scm to generate a version file from your version control system, then flit to build the package.
Keywords: flit,pep518,build,packaging,scm
Author-email: Will Da Silva <will@willdasilva.xyz>
Requires-Python: >=3.6
Classifier: Development Status :: 5 - Production/Stable
Classifier: Intended Audience :: Developers
Classifier: License :: OSI Approved
Classifier: License :: OSI Approved :: MIT License
Classifier: Programming Language :: Python
Classifier: Topic :: Software Development
Classifier: Topic :: Software Development :: Build Tools
Requires-Dist: flit-core~=3.5
Requires-Dist: setuptools_scm>=6.4
Requires-Dist: tomli; python_version < '3.11'
Project-URL: documentation, https://gitlab.com/WillDaSilva/flit_scm
Project-URL: homepage, https://gitlab.com/WillDaSilva/flit_scm
Project-URL: repository, https://gitlab.com/WillDaSilva/flit_scm
